uniform_vlm/__init__.py
uniform_vlm/cli.py
uniform_vlm/warmup.py
uniform_vlm/infer/__init__.py
uniform_vlm/infer/dataset.py
uniform_vlm/infer/format.py
uniform_vlm/infer/run.py
uniform_vlm/train/__init__.py
uniform_vlm/train/dataset.py
uniform_vlm/train/run.py
uniform_vlm-0.1.3.dist-info/METADATA
uniform_vlm-0.1.3.dist-info/WHEEL
uniform_vlm-0.1.3.dist-info/entry_points.txt
uniform_vlm-0.1.3.dist-info/top_level.txt
uniform_vlm-0.1.3.dist-info/RECORD
